pycharmers/__init__.py
pycharmers/__meta__.py
pycharmers/cli/__init__.py
pycharmers/cli/_clipath.py
pycharmers/cli/book2img.py
pycharmers/cli/cvCascades.py
pycharmers/cli/cvPaperScanner.py
pycharmers/cli/cvPencilSketch.py
pycharmers/cli/cvWindow.py
pycharmers/cli/form_auto_fill_in.py
pycharmers/cli/jupyter_arrange.py
pycharmers/cli/openBrowser.py
pycharmers/cli/pdfmine.py
pycharmers/cli/regexp_replacement.py
pycharmers/cli/render_template.py
pycharmers/cli/requirements.py
pycharmers/cli/revise_text.py
pycharmers/cli/show.py
pycharmers/cli/tweetile.py
pycharmers/cli/video2gif.py
pycharmers/cli/video_of_lyric.py
pycharmers/cli/video_of_typing.py
pycharmers/matplotlib/__init__.py
pycharmers/matplotlib/cmaps.py
pycharmers/matplotlib/layout.py
pycharmers/matplotlib/plot2d.py
pycharmers/matplotlib/plot3d.py
pycharmers/opencv/__init__.py
pycharmers/opencv/_cvpath.py
pycharmers/opencv/backsub.py
pycharmers/opencv/binary.py
pycharmers/opencv/cascade.py
pycharmers/opencv/cvui.py
pycharmers/opencv/drawing.py
pycharmers/opencv/editing.py
pycharmers/opencv/morphology.py
pycharmers/opencv/project.py
pycharmers/opencv/tracking.py
pycharmers/opencv/video_image_handler.py
pycharmers/opencv/windows.py
pycharmers/sdk/__init__.py
pycharmers/sdk/_base.py
pycharmers/sdk/github.py
pycharmers/sdk/google_drive.py
pycharmers/sdk/mysql.py
pycharmers/sdk/slack.py
pycharmers/sdk/trello.py
pycharmers/templates/_macros/utils.html
pycharmers/templates/base.html
pycharmers/templates/def.html
pycharmers/templates/fonts.html
pycharmers/templates/style.html
pycharmers/utils/__init__.py
pycharmers/utils/_colorings.py
pycharmers/utils/_exceptions.py
pycharmers/utils/_path.py
pycharmers/utils/_warnings.py
pycharmers/utils/argparse_utils.py
pycharmers/utils/color_utils.py
pycharmers/utils/download_utils.py
pycharmers/utils/driver_utils.py
pycharmers/utils/environ_utils.py
pycharmers/utils/generic_utils.py
pycharmers/utils/inspect_utils.py
pycharmers/utils/json_utils.py
pycharmers/utils/monitor_utils.py
python_charmers-0.2.0.dist-info/entry_points.txt
python_charmers-0.2.0.dist-info/LICENSE
python_charmers-0.2.0.dist-info/WHEEL
python_charmers-0.2.0.dist-info/METADATA
python_charmers-0.2.0.dist-info/RECORD
