Metadata-Version: 2.1
Name: python-charmers
Version: 0.2.0
Summary: A collection of useful python programs.
Home-page: https://iwasakishuto.github.io/Python-Charmers/
License: MIT
Author: iwasakishuto
Author-email: cabernet.rock@gmail.com
Requires-Python: >=3.8,<4.0
Classifier: Development Status :: 3 - Alpha
Classifier: Environment :: Console
Classifier: Environment :: MacOS X
Classifier: Intended Audience :: Developers
Classifier: License :: OSI Approved :: MIT License
Classifier: Programming Language :: Python :: 3
Classifier: Programming Language :: Python :: 3.8
Classifier: Programming Language :: Python :: 3.9
Classifier: Topic :: Software Development :: Libraries :: Python Modules
Requires-Dist: Jinja2 (>=2.11.3,<3.0.0)
Requires-Dist: Pillow (>=8.2.0,<9.0.0)
Requires-Dist: PyDrive (>=1.3.1,<2.0.0)
Requires-Dist: PyMuPDF (>=1.18.13,<2.0.0)
Requires-Dist: beautifulsoup4 (>=4.9.3,<5.0.0)
Requires-Dist: camelot-py (>=0.8.2,<0.9.0)
Requires-Dist: html5lib (>=1.1,<2.0)
Requires-Dist: lxml (>=4.6.3,<5.0.0)
Requires-Dist: matplotlib (>=3.4.2,<4.0.0)
Requires-Dist: moviepy (>=1.0.3,<2.0.0)
Requires-Dist: mysqlclient (>=2.0.3,<3.0.0)
Requires-Dist: nptyping (>=1.4.2,<2.0.0)
Requires-Dist: numpy (>=1.20.3,<2.0.0)
Requires-Dist: numpy-stl (>=2.16.0,<3.0.0)
Requires-Dist: opencv-contrib-python (>=4.5.2,<5.0.0)
Requires-Dist: paramiko (>=2.7.2,<3.0.0)
Requires-Dist: python-docx (>=0.8.11,<0.9.0)
Requires-Dist: python-dotenv (>=0.17.1,<0.18.0)
Requires-Dist: python-xlib (>=0.29,<0.30)
Requires-Dist: requests (>=2.25.1,<3.0.0)
Requires-Dist: scipy (==1.4.1)
Requires-Dist: scp (>=0.13.3,<0.14.0)
Requires-Dist: selenium (>=3.141.0,<4.0.0)
Requires-Dist: wcwidth (>=0.2.5,<0.3.0)
Project-URL: Bug Tracker, https://github.com/iwasakishuto/PythonUtils/issues
Project-URL: Repository, https://github.com/iwasakishuto/Python-Charmers
Project-URL: Source Code, https://github.com/iwasakishuto/PythonUtils
Project-URL: Say Thanks!, https://twitter.com/cabernet_rock
